ms4/__init__.py
ms4/ms4.py
ms4-2.10.0.dist-info/LICENSE
ms4-2.10.0.dist-info/METADATA
ms4-2.10.0.dist-info/WHEEL
ms4-2.10.0.dist-info/top_level.txt
ms4-2.10.0.dist-info/RECORD
